tortoise_pagination/__init__.py
tortoise_pagination/pagination.py
tortoise_pagination-1.3.2.dist-info/METADATA
tortoise_pagination-1.3.2.dist-info/WHEEL
tortoise_pagination-1.3.2.dist-info/RECORD
