Metadata-Version: 2.3
Name: tortoise-pagination
Version: 1.3.2
Summary: Pagination for Tortoise-ORM on FastAPI
License: MIT
Author: Sebastien Nicolet
Author-email: snicolet95@gmail.com
Requires-Python: >=3.12,<4.0
Classifier: License :: OSI Approved :: MIT License
Classifier: Programming Language :: Python :: 3
Classifier: Programming Language :: Python :: 3.12
Classifier: Programming Language :: Python :: 3.13
Requires-Dist: asyncpg (>=0.30.0,<0.31.0)
Requires-Dist: fastapi (>=0.104.1)
Requires-Dist: pydantic (>2.0.0)
Requires-Dist: tortoise-orm (>=0.23.0,<0.26.0)
